dharma/__init__.py
dharma/__main__.py
dharma/__version__.py
dharma/dharma.py
dharma/settings.py
dharma/core/__init__.py
dharma/core/dharma.py
dharma/core/extensions.py
dharma/core/websocket.py
dharma/grammars/arguments.dg
dharma/grammars/calls.dg
dharma/grammars/common.dg
dharma/grammars/constructors.dg
dharma/grammars/fuzzer_block.dg
dharma/grammars/fuzzers.dg
dharma/grammars/js.dg
dharma/grammars/jsarray.dg
dharma/grammars/jsclass.dg
dharma/grammars/jsfunction.dg
dharma/grammars/jsobject.dg
dharma/grammars/jsproxy.dg
dharma/grammars/jssymbol.dg
dharma/grammars/jstypedarray.dg
dharma/grammars/mutators.dg
dharma/grammars/properties.dg
dharma/grammars/properties.dg.bak
dharma/grammars/traps.dg
dharma/grammars/variables.dg
dharma_callback_fuzzer-1.2.4.dist-info/DESCRIPTION.rst
dharma_callback_fuzzer-1.2.4.dist-info/METADATA
dharma_callback_fuzzer-1.2.4.dist-info/RECORD
dharma_callback_fuzzer-1.2.4.dist-info/WHEEL
dharma_callback_fuzzer-1.2.4.dist-info/entry_points.txt
dharma_callback_fuzzer-1.2.4.dist-info/metadata.json
dharma_callback_fuzzer-1.2.4.dist-info/top_level.txt
